{"feed":[{"spacing":"small","type":"__spacer__"},{"id":"10461905","category":"Elm və Texnologiya","author":"aqreqator.az","published_at":"2023-02-02T13:42:00:000","title":"Türkiyədə ilk qırıcı təyyarənin mühərriki işə salındı – Martda havaya qalxacaq - VİDEO","description":"","is_premium":false,"is_content_overlaid":false,"type":"__post_large__","image_url":"https://aqreqator.az/img/pics/large/2023-02/1569438_0kq0dyg0zf.jpg","action":{"article_id":"10461905","type":"__navigate_to_article__"}},{"type":"__divider_horizontal__"},{"spacing":"small","type":"__spacer__"},{"id":"10461912","category":"Elm və Texnologiya","author":"aqreqator.az","published_at":"2023-02-02T13:23:00:000","title":"29 yaşlı nazir buna görə tənqid olundu","description":"","is_premium":false,"is_content_overlaid":false,"type":"__post_small__","image_url":"https://aqreqator.az/img/pics/large/2023-02/1569389_lc0u98j97h.jpg","action":{"article_id":"10461912","type":"__navigate_to_article__"}},{"type":"__divider_horizontal__"},{"spacing":"small","type":"__spacer__"},{"id":"10463390","category":"Elm və Texnologiya","author":"azertag.az","published_at":"2023-02-02T12:48:00:000","title":"AMEA-da gənclərin peşəkar mütəxəssis kimi yetişmələri üçün əlverişli iş şəraiti yaradılıb","description":"Bu gün Azərbaycan gəncliyi ictimai həyatın bütün sahələrində öz fəallığı ilə seçilir. Gənclər ölkə rəhbərliyinin siyasi, iqtisadi, humanitar, sosial istiqamətlər üzrə həyata keçirdiyi tədbirlərə hər zaman dəstək verir, cəmiyyətdə dayanıqlı sabitliyin və ardıcıl inkişafın təmin olunmasında","is_premium":false,"is_content_overlaid":false,"type":"__post_small__","image_url":"https://azertag.az/files/2023/1/1200x630/16753283674887149200_1200x630.jpg","action":{"article_id":"10463390","type":"__navigate_to_article__"}},{"type":"__divider_horizontal__"},{"spacing":"small","type":"__spacer__"},{"id":"10461925","category":"Elm və Texnologiya","author":"aqreqator.az","published_at":"2023-02-02T11:22:00:000","title":"\"Sony\"nin prezidenti istefa verdi","description":"","is_premium":false,"is_content_overlaid":false,"type":"__post_medium__","image_url":"https://aqreqator.az/img/pics/large/2023-02/1569270_6qp8ml3otk.jpg","action":{"article_id":"10461925","type":"__navigate_to_article__"}},{"type":"__divider_horizontal__"},{"spacing":"small","type":"__spacer__"},{"id":"10462598","category":"Elm və Texnologiya","author":"fed.az","published_at":"2023-02-02T09:16:33:000","title":"Azercell bütün tarif paketləri üçün - YENİ QİYMƏTLƏRİ AÇIQLADI - SİYAHI","description":"azercell","is_premium":false,"is_content_overlaid":false,"type":"__post_small__","image_url":"https://fed.az/upload/news/362547.jpg","action":{"article_id":"10462598","type":"__navigate_to_article__"}},{"type":"__divider_horizontal__"},{"spacing":"small","type":"__spacer__"},{"id":"10461936","category":"Elm və Texnologiya","author":"aqreqator.az","published_at":"2023-02-02T08:56:00:000","title":"Bu gecə mamontların dövründə yaşayan insanların gördüklərinin şahidi olacağıq - FOTO/VİDEO","description":"","is_premium":false,"is_content_overlaid":false,"type":"__post_small__","image_url":"https://aqreqator.az/img/pics/large/2023-02/1569124_0da4gcr3ov.jpg","action":{"article_id":"10461936","type":"__navigate_to_article__"}},{"type":"__divider_horizontal__"},{"spacing":"small","type":"__spacer__"},{"id":"10461904","category":"Elm və Texnologiya","author":"sia.az","published_at":"2023-02-02T06:33:00:000","title":"\"Netflix\"dən yaxşı və pis xəbər - DİQQƏT!","description":"","is_premium":false,"is_content_overlaid":false,"type":"__post_large__","image_url":"https://sia.az/storage/2023/02/02/t65789.jpg","action":{"article_id":"10461904","type":"__navigate_to_article__"}},{"type":"__divider_horizontal__"},{"spacing":"small","type":"__spacer__"},{"id":"10461469","category":"Elm və Texnologiya","author":"lent.az","published_at":"2023-02-02T04:16:00:000","title":"TEKNOFEST bu il 3 şəhərdə keçiriləcək","description":"","is_premium":false,"is_content_overlaid":false,"type":"__post_small__","image_url":"https://lent.az/storage/news/2023/february/02/big/63dafe6fc847063dafe6fc8471167529636763dafe6fc846e63dafe6fc846f.jpg","action":{"article_id":"10461469","type":"__navigate_to_article__"}},{"type":"__divider_horizontal__"}],"total_count":8}