{"title":"Poqosyandan LAVROVA: “Siz Əliyevdən üzr istəməlisiniz, çünki 7 rayonu işğal etməyə yardım göstərmisiz”","content":[{"category":"entertainment","author":"konkret.az","published_at":"2023-02-04T07:20:00.000","image_url":"https://konkret.az/cloud/uploads/2023/02/poqosyan.jpg","title":"Poqosyandan LAVROVA: “Siz Əliyevdən üzr istəməlisiniz, çünki 7 rayonu işğal etməyə yardım göstərmisiz”","is_preview":true,"is_premium":false,"type":"__article_introduction__"}],"url":"https://konkret.az/poqosyandan-lavrova-siz-eliyevden-uzr-istemelisiniz-cunki-7-rayonu-isgal-etmeye-yardim-gostermisiz","is_premium":false,"is_preview":true,"total_count":1}