{"title":"Bakıda evdən gedən azyaşlını valideynləri axtarmır - Polis sığınacağa yerləşdirdi","content":[{"category":"science","author":"aqreqator.az","published_at":"2023-02-04T12:12:00.000","image_url":"https://aqreqator.az/img/pics/large/2023-02/1571149_9otd10f0ia.jpg","title":"Bakıda evdən gedən azyaşlını valideynləri axtarmır - Polis sığınacağa yerləşdirdi","is_preview":true,"is_premium":false,"type":"__article_introduction__"}],"url":"https://aqreqator.az/az/cemiyyet/2374659","is_premium":false,"is_preview":true,"total_count":1}