{"title":"Cəbəllütariq İspaniyanı gömrük əməliyyatı ilə bağlı “suverenliyi kobud şəkildə pozmaqda” ittiham edir","content":[{"category":"business","author":"az24saat.org","published_at":"2023-02-04T06:10:40.000","image_url":"https://www.az24saat.org/wp-content/uploads/2023/02/Cəbəllutariq-Ispaniyani-gomruk-əməliyyati-ilə-bagli-suverenliyi-kobud-səkildə-pozmaqda-scaled.jpg","title":"Cəbəllütariq İspaniyanı gömrük əməliyyatı ilə bağlı “suverenliyi kobud şəkildə pozmaqda” ittiham edir","is_preview":true,"is_premium":false,"type":"__article_introduction__"}],"url":"https://www.az24saat.org/cəbəllutariq-ispaniyani-gomruk-əməliyyati-ilə-bagli-suverenliyi-kobud-səkildə-pozmaqda-ittiham-edir","is_premium":false,"is_preview":true,"total_count":1}