{"title":"Fevral ayında immun sistemini qoruyacaq QİDA","content":[{"category":"saglamliq","author":"turpkimi.com","published_at":"2023-02-23T00:14:01.000","image_url":"https://turpkimi.com/files/posts/original/2023/2/23/b2ff0686-6834-4a2a-a105-4edb623c100e/f13478d3ef0a4552870113c6f2e2b199.jpg","title":"Fevral ayında immun sistemini qoruyacaq QİDA","is_preview":true,"is_premium":false,"type":"__article_introduction__"}],"url":"https://turpkimi.com/az/blog/fevral-ayinda-immun-sistemini-qoruyacaq-qida","is_premium":false,"is_preview":true,"total_count":1}