{"title":"İslam İnkişaf Bankının prezidenti Azərbaycana gələcək","content":[{"category":"diger","author":"525.az","published_at":"2023-02-24T10:14:00.000","image_url":"https://525.az/img/pics/large/2023-02/257839_qoxn7g4ise.jpg","title":"İslam İnkişaf Bankının prezidenti Azərbaycana gələcək","is_preview":true,"is_premium":false,"type":"__article_introduction__"}],"url":"https://525.az/news/214881-islam-inkisaf-bankinin-prezidenti-azerbaycana-gelecek","is_premium":false,"is_preview":true,"total_count":1}