{"title":"Ramazan ayı bu tarixdə başlayacaq - FOTO","content":[{"category":"cemiyyet","author":"xezerxeber.az","published_at":"2023-02-23T12:12:25.000","image_url":"https://cdn.xezerxeber.az/main/U459KRRs6pJkwTmpeA6F68HNGPpsZe7pMaUFRyUr.jpg","title":"Ramazan ayı bu tarixdə başlayacaq - FOTO","is_preview":true,"is_premium":false,"type":"__article_introduction__"}],"url":"https://www.xezerxeber.az/news/cemiyyet/395699/ramazan-ayi-bu-tarixde-baslayacaq","is_premium":false,"is_preview":true,"total_count":1}