{"title":"ABŞ Dövlət Departamenti Azərbaycan və Ermənistana üçtərəfli görüş təklifi göndərib","content":[{"category":"siyaset","author":"525.az","published_at":"2023-02-24T10:49:00.000","image_url":"https://525.az/img/pics/large/2023-02/257845_zx2is3j9gt.jpg","title":"ABŞ Dövlət Departamenti Azərbaycan və Ermənistana üçtərəfli görüş təklifi göndərib","is_preview":true,"is_premium":false,"type":"__article_introduction__"}],"url":"https://525.az/news/214887-abs-dovlet-departamenti-azerbaycan-ve-ermenistana-ucterefli-gorus-teklifi-gonderib","is_premium":false,"is_preview":true,"total_count":1}