{"title":"Milli Arxiv İdarəsindən \"Koneks Construction\"a 9,2 milyon manatlıq sifariş - TENDER NƏTİCƏSİ","content":[{"category":"diger","author":"fed.az","published_at":"2023-02-24T09:08:06.000","image_url":"https://fed.az/upload/news/1376789.jpg","title":"Milli Arxiv İdarəsindən \"Koneks Construction\"a 9,2 milyon manatlıq sifariş - TENDER NƏTİCƏSİ","is_preview":true,"is_premium":false,"type":"__article_introduction__"}],"url":"https://fed.az/az/tenderler/milli-arxiv-idaresinden-quotkoneks-constructionquota-9-milyon-manatliq-sifaris-tender-neticesi-156036","is_premium":false,"is_preview":true,"total_count":1}