{"title":"Türkiyə İsveç və Finlandiya ilə danışıqlara qayıdır - Bu tarixdə","content":[{"category":"olke","author":"modern.az","published_at":"2023-02-23T09:24:28.000","image_url":"https://files.modern.az/articles/2023/02/23/1677130120_1059584472_2_0_839_471_1920x0_80_0_0_1a9d37fd26c704542694091bb81f97e8.jpg","title":"Türkiyə İsveç və Finlandiya ilə danışıqlara qayıdır - Bu tarixdə","is_preview":true,"is_premium":false,"type":"__article_introduction__"}],"url":"https://modern.az/dunya/397272/turkiyenin-isvec-ve-finlandiya-ile-danisiqlari-berpa-edeceyi-tarix","is_premium":false,"is_preview":true,"total_count":1}