{"title":"Bölgələrdə heyvandarlığa maraq niyə azalıb? - VİDEO","content":[{"category":"senaye","author":"fins.az","published_at":"2023-02-23T18:48:07.000","image_url":"https://fins.az/file/articles/2023/02/23/1677153492_13391674.jpg","title":"Bölgələrdə heyvandarlığa maraq niyə azalıb? - VİDEO","is_preview":true,"is_premium":false,"type":"__article_introduction__"}],"url":"https://fins.az/aqro/294885/blgelerde-heyvandarlia-maraq-niye-azalib-video","is_premium":false,"is_preview":true,"total_count":1}