{"title":"Dünyanın ən çox sanksiyaya məruz qalan ölkəsi…","content":[{"category":"siyaset","author":"nocomment.az","published_at":"2023-02-23T09:51:00.000","image_url":"https://nocomment.az/public/cloud/2020/12/nocomment_abed8401124c79b656d0ecddacab2a4d_rn2qs45gjfeuhit17x96-e1614599648326.jpg","title":"Dünyanın ən çox sanksiyaya məruz qalan ölkəsi…","is_preview":true,"is_premium":false,"type":"__article_introduction__"}],"url":"https://nocomment.az/dunyanin-en-cox-sanksiyaya-meruz-qalan-olkesi","is_premium":false,"is_preview":true,"total_count":1}