{"title":"Artımdan sonra müəllimlər nə qədər maaş alacaq? – SADƏ İZAH","content":[{"category":"gundem","author":"savash.org","published_at":"2023-02-23T17:25:07.000","image_url":"https://www.savash.org/wp-content/uploads/2023/02/1677166334_1677165007_181006a23c286ec28afd82f8a5513af71629529113_untitled-1-jpg.jpg","title":"Artımdan sonra müəllimlər nə qədər maaş alacaq? – SADƏ İZAH","is_preview":true,"is_premium":false,"type":"__article_introduction__"}],"url":"https://savash.org/manet/59337-artimdan-sonra-muəllimlər-nə-qədər-maas-alacaq-sadə-izah.html","is_premium":false,"is_preview":true,"total_count":1}