{"title":"ABŞ-ın kommersiya neft ehtiyatları 480 mln. barelə yaxınlaşıb","content":[{"category":"siyaset","author":"fins.az","published_at":"2023-02-24T20:11:06.000","image_url":"https://fins.az/file/articles/2023/02/24/1677221647_63f84f60a1e9d63f84f60a1e9e167721763263f84f60a1e9b63f84f60a1e9c.jpeg","title":"ABŞ-ın kommersiya neft ehtiyatları 480 mln. barelə yaxınlaşıb","is_preview":true,"is_premium":false,"type":"__article_introduction__"}],"url":"https://fins.az/senaye/294925/abs-in-kommersiya-neft-ehtiyatlari-480-mln-barele-yaxinlasib","is_premium":false,"is_preview":true,"total_count":1}