{"title":"Cəlilabadda modul tipli məktəbin tikinti işləri yekunlaşmaq üzrədir","content":[{"category":"elmtexnologiya","author":"report.az","published_at":"2023-02-24T10:48:00.000","image_url":"https://static.report.az/photo/25b2f267-88a4-3e7d-93d9-5aeb72e40a20_824.jpg","title":"Cəlilabadda modul tipli məktəbin tikinti işləri yekunlaşmaq üzrədir","is_preview":true,"is_premium":false,"type":"__article_introduction__"}],"url":"https://report.az/elm-ve-tehsil-xeberleri/celilabadda-modul-tipli-mektebin-tikinti-isleri-yekunlasmaq-uzredir","is_premium":false,"is_preview":true,"total_count":1}