{"title":"“Kiyev Dnestryanıda təxribata hazırlaşır“ - Rusiya Müdafiə Nazirliyinin uydurması","content":[{"category":"gundem","author":"moderator.az","published_at":"2023-02-23T17:39:00.000","image_url":"https://moderator.az/file/articles/2023/02/23/1677159710_87.jpg","title":"“Kiyev Dnestryanıda təxribata hazırlaşır“ - Rusiya Müdafiə Nazirliyinin uydurması","is_preview":true,"is_premium":false,"type":"__article_introduction__"}],"url":"https://moderator.az/az/ekskluziv/602912/kiyev-dnestryanida-texribata-hazirlasir-rusiya-mudafie-nazirliyinin-uydurmasi","is_premium":false,"is_preview":true,"total_count":1}