{"title":"\"Putinin nüvə silahından istifadə edəcəyini düşünmürəm\" - Bayden","content":[{"category":"siyaset","author":"manset.az","published_at":"2023-02-23T21:50:00.000","image_url":"https://manset.az//storage/2023/february/23/abd_baskani_biden_putin_in_nukleer_silah_15655026_amp1677174667.jpg","title":"\"Putinin nüvə silahından istifadə edəcəyini düşünmürəm\" - Bayden","is_preview":true,"is_premium":false,"type":"__article_introduction__"}],"url":"https://manset.az/news/62076/putinin-nuve-silahindan-istifade-edeceyini-dusunmurem-bayden","is_premium":false,"is_preview":true,"total_count":1}