{"title":"Ukrayna müharibəsi ilə bağlı şok: \"Hələ bir il də davam edəcək\"","content":[{"category":"diger","author":"teleqraf.com","published_at":"2023-02-23T15:26:14.000","image_url":"https://teleqraf.com/storage/2022/06/30/rusya-dan-ukrayna-isgalinin-55-gununde-savasin-14881089_1554_o.jpg","title":"Ukrayna müharibəsi ilə bağlı şok: \"Hələ bir il də davam edəcək\"","is_preview":true,"is_premium":false,"type":"__article_introduction__"}],"url":"https://teleqraf.com/news/dunya/368404.html","is_premium":false,"is_preview":true,"total_count":1}