{"title":"Lalə Şövkət siyasətə qayıdır? – “...Müzakirə oluna bilər”","content":[{"category":"olke","author":"dia.az","published_at":"2023-02-24T15:30:00.000","image_url":"https://dia.az/uploads/posts/2023-02/thumbs/1677238220_0001.jpg","title":"Lalə Şövkət siyasətə qayıdır? – “...Müzakirə oluna bilər”","is_preview":true,"is_premium":false,"type":"__article_introduction__"}],"url":"https://www.dia.az/8/368239-lale-shovket-siyasete-qayidir.html","is_premium":false,"is_preview":true,"total_count":1}