{"title":"Daha bir keçmiş rektor Azərbaycandan QAÇAQ DÜŞÜB - İLGİNC FAKT","content":[{"category":"idman","author":"dia.az","published_at":"2023-02-23T09:53:00.000","image_url":"https://dia.az/uploads/posts/2023-02/thumbs/1677131604_0001.jpg","title":"Daha bir keçmiş rektor Azərbaycandan QAÇAQ DÜŞÜB - İLGİNC FAKT","is_preview":true,"is_premium":false,"type":"__article_introduction__"}],"url":"https://www.dia.az/8/368083-daha-bir-kechmish-rektor-azerbaycandan-qachaq-dushub.html","is_premium":false,"is_preview":true,"total_count":1}