{"title":"“Azərenerji” və “Azərişıq” ASC-lər parçalanacaq, yeni tənzimləyici orqan yaranacaq - AÇIQLAMA","content":[{"category":"hava","author":"dia.az","published_at":"2023-02-24T16:59:00.000","image_url":"https://dia.az/uploads/posts/2023-02/thumbs/1677243544_0001.jpg","title":"“Azərenerji” və “Azərişıq” ASC-lər parçalanacaq, yeni tənzimləyici orqan yaranacaq - AÇIQLAMA","is_preview":true,"is_premium":false,"type":"__article_introduction__"}],"url":"https://www.dia.az/8/368255-azerenerji-ve-azerishiq-asc-ler-parchalanacaq-yeni-tenzimleyici-orqan-yaranacaq.html","is_premium":false,"is_preview":true,"total_count":1}