{"title":"Bu dərmanların satışına güzəştlər edilə bilər","content":[{"category":"saglamliq","author":"olke.az","published_at":"2023-02-24T16:21:00.000","image_url":"https://olke.az/file/articles/2023/02/24/1677241307_2455574.jpg","title":"Bu dərmanların satışına güzəştlər edilə bilər","is_preview":true,"is_premium":false,"type":"__article_introduction__"}],"url":"https://olke.az/iqtisadiyyat/315649/bu-dermanlarin-satisina-guzestler-edile-biler","is_premium":false,"is_preview":true,"total_count":1}