{"title":"Paşinyan Qarabağı Azərbaycanın tərkibində görür","content":[{"category":"siyaset","author":"nocomment.az","published_at":"2023-02-24T12:15:00.000","image_url":"https://nocomment.az/public/cloud/2020/12/nocomment_768f1bbd185b27192e7ddcef745042fb_2hz3wgxnb4lfrqa8uojv.jpg?v=1607754370","title":"Paşinyan Qarabağı Azərbaycanın tərkibində görür","is_preview":true,"is_premium":false,"type":"__article_introduction__"}],"url":"https://nocomment.az/pasinyan-hakimiyyeti-qarabagi-azerbaycanin-terkibinde-gorur-ohanyan","is_premium":false,"is_preview":true,"total_count":1}