{"title":"Katalonlara olmaz, ermənilərə olar? - Deputat Avropanın ikili standartından danışdı","content":[{"category":"siyaset","author":"sfera.az","published_at":"2023-02-24T12:56:00.000","image_url":"https://sfera.az/file/articles/2023/02/24/1677228796_4015b63ce6a0c29b8dde226064a331a3-1.jpg","title":"Katalonlara olmaz, ermənilərə olar? - Deputat Avropanın ikili standartından danışdı","is_preview":true,"is_premium":false,"type":"__article_introduction__"}],"url":"https://sfera.az/siyaset/211050/katalonlara-olmaz-ermenilere-olar-deputat-avropanin-ikili-standartindan-danisdi","is_premium":false,"is_preview":true,"total_count":1}