{"title":"İstanbulda silahlı hücuma hazırlaşan şəxslər yaxalandı","content":[{"category":"diger","author":"olke.az","published_at":"2023-02-24T12:50:00.000","image_url":"https://olke.az/file/articles/2023/02/24/1677223372_screenshot_10.jpg","title":"İstanbulda silahlı hücuma hazırlaşan şəxslər yaxalandı","is_preview":true,"is_premium":false,"type":"__article_introduction__"}],"url":"https://olke.az/dunya/315590/istanbulda-silahli-hucuma-hazirlasan-sexsler-yaxalandi","is_premium":false,"is_preview":true,"total_count":1}