{"title":"Bu avtomobillərin hərəkəti ilə bağlı qaydalar sərtləşdirilir","content":[{"category":"iqtisadiyyat","author":"qaynarinfo.az","published_at":"2023-02-24T15:34:00.000","image_url":"https://cdn.qaynarinfo.az/2023-02/be546aca940fe6e5ddfe0a5b2852359e1676638700_646e2033733e9f821c1e4e41d27002d6untitled-1-jpg-jpg.jpg","title":"Bu avtomobillərin hərəkəti ilə bağlı qaydalar sərtləşdirilir","is_preview":true,"is_premium":false,"type":"__article_introduction__"}],"url":"https://qaynarinfo.az/az/bu-avtomobillerin-hereketi-ile-bagli-qaydalar-sertlesdirilir","is_premium":false,"is_preview":true,"total_count":1}