{"title":"“O, öz fikirlərini yox, Rusiya siyasi elitasının fikirlərini səsləndirib”-ŞƏRH","content":[{"category":"siyaset","author":"busaat.az","published_at":"2023-02-24T14:16:00.000","image_url":"https://static.busaat.az/core/storage/2022/03/medvedev.jpg","title":"“O, öz fikirlərini yox, Rusiya siyasi elitasının fikirlərini səsləndirib”-ŞƏRH","is_preview":true,"is_premium":false,"type":"__article_introduction__"}],"url":"https://busaat.az/o-oz-fikirlerini-yox-rusiya-siyasi-elitasinin-fikirlerini-seslendirib-serh","is_premium":false,"is_preview":true,"total_count":1}