{"title":"\"\"Trendyol”dan sifarişlər heç bir halda qadağan edilə bilməz\" - Vüqar Bayramov","content":[{"category":"olke","author":"redaktor.az","published_at":"2023-02-24T14:59:00.000","image_url":"https://img.redaktor.az/news/2023/02/photo_195669.jpg?v=MjAyMy0wMi0yNCAxNToxMDowNg==","title":"\"\"Trendyol”dan sifarişlər heç bir halda qadağan edilə bilməz\" - Vüqar Bayramov","is_preview":true,"is_premium":false,"type":"__article_introduction__"}],"url":"https://redaktor.az/news/country/195669-trendyoldan-sifarisler-hec-bir-halda-qadagan-edile-bilmez","is_premium":false,"is_preview":true,"total_count":1}