{"title":"Dövlət Agentliyində Xocalı soyqırımının 31-ci ildönümü ilə əlaqədar tədbir keçirilib","content":[{"category":"siyaset","author":"report.az","published_at":"2023-02-24T18:12:00.000","image_url":"https://static.report.az/photo/2d2d9256-7b6a-3a60-bd36-88c8a7ff015d_824.jpg","title":"Dövlət Agentliyində Xocalı soyqırımının 31-ci ildönümü ilə əlaqədar tədbir keçirilib","is_preview":true,"is_premium":false,"type":"__article_introduction__"}],"url":"https://report.az/daxili-siyaset/qeyri-hokumet-teskilatlarina-dovlet-desteyi-agentliyinde-xocali-soyqiriminin-31-ci-ildonumu-ile-elaqedar-tedbir-kecirilib","is_premium":false,"is_preview":true,"total_count":1}