{"title":"“Facebook” bayrağımızı erməni bayrağına çevirdi: Siyasi SABOTAJ, yoxsa texniki PROBLEM? – AÇIQLAMA/FOTO","content":[{"category":"idman","author":"yenicag.az","published_at":"2023-02-25T10:15:31.000","image_url":"https://cdn.yenicag.az/files/uploads/2023/02/b3959e39-c081-4b24-b24d-d2de67bd4ecf.jpg","title":"“Facebook” bayrağımızı erməni bayrağına çevirdi: Siyasi SABOTAJ, yoxsa texniki PROBLEM? – AÇIQLAMA/FOTO","is_preview":true,"is_premium":false,"type":"__article_introduction__"}],"url":"https://yenicag.az/facebook-bayragimizi-ermeni-bayragina-cevirdi-siyasi-sabotaj-yoxsa-texniki-problem-aciqlama-foto","is_premium":false,"is_preview":true,"total_count":1}