{"title":"BVF kriptovalyuta fəaliyyət planı hazırlayır, qanuni tender statusuna qarşı tövsiyə edir","content":[{"category":"iqtisadiyyat","author":"az24saat.org","published_at":"2023-02-24T13:14:35.000","image_url":"https://www.az24saat.org/wp-content/uploads/2023/02/BVF-kriptovalyuta-fəaliyyət-plani-hazirlayir-qanuni-tender-statusuna-qarsi-tovsiyə-scaled.jpg","title":"BVF kriptovalyuta fəaliyyət planı hazırlayır, qanuni tender statusuna qarşı tövsiyə edir","is_preview":true,"is_premium":false,"type":"__article_introduction__"}],"url":"https://www.az24saat.org/bvf-kriptovalyuta-fəaliyyət-plani-hazirlayir-qanuni-tender-statusuna-qarsi-tovsiyə-edir","is_premium":false,"is_preview":true,"total_count":1}