{"title":"Daha 3 rayona internetlə bilet almaq mümkün oldu - SİYAHI","content":[{"category":"olke","author":"fed.az","published_at":"2023-02-25T11:26:08.000","image_url":"https://fed.az/upload/news/697217.jpg","title":"Daha 3 rayona internetlə bilet almaq mümkün oldu - SİYAHI","is_preview":true,"is_premium":false,"type":"__article_introduction__"}],"url":"https://fed.az/az/neqliyyat/daha-3-rayona-internetle-bilet-almaq-mumkun-oldu-siyahi-156211","is_premium":false,"is_preview":true,"total_count":1}