{"title":"Azərbaycanın xaricdəki səfirliyinin əməkdaşı - SƏFİRLİYİN 200 MİN DOLLARINI - MƏRC OYUNLARINDA UDUZUB","content":[{"category":"kriminal","author":"fed.az","published_at":"2023-02-25T14:03:54.000","image_url":"https://fed.az/upload/news/3484003.jpg","title":"Azərbaycanın xaricdəki səfirliyinin əməkdaşı - SƏFİRLİYİN 200 MİN DOLLARINI - MƏRC OYUNLARINDA UDUZUB","is_preview":true,"is_premium":false,"type":"__article_introduction__"}],"url":"https://fed.az/az/huquq/azerbaycanin-xaricdeki-sefirliyinin-emekdasi-sefirliyin-200-min-dollarini-merc-oyunlarinda-uduzub-156229","is_premium":false,"is_preview":true,"total_count":1}