{"title":"Azərbaycanda \"Trendyol\"un fəaliyyətinin məhdudlaşdırılmasına ekspert münasibəti","content":[{"category":"diger","author":"turpkimi.com","published_at":"2023-02-24T20:51:01.000","image_url":"https://turpkimi.com/files/posts/original/2023/2/24/26aba82f-5df9-4317-8e72-5099689a97f2/0551bef75e7c49fb8b49e8db21d12250.png","title":"Azərbaycanda \"Trendyol\"un fəaliyyətinin məhdudlaşdırılmasına ekspert münasibəti","is_preview":true,"is_premium":false,"type":"__article_introduction__"}],"url":"https://turpkimi.com/az/blog/azerbaycanda-trendyol-un-fealiyyetinin-mehdudlasdirilmasina-ekspert-munasibeti","is_premium":false,"is_preview":true,"total_count":1}