{"title":"ABŞ Çində istehsal edilən S.Koreya çiplərinin səviyyəsini məhdudlaşdıra bilər – ABŞ rəsmisi","content":[{"category":"siyaset","author":"az24saat.org","published_at":"2023-02-24T16:13:59.000","image_url":"https://www.az24saat.org/wp-content/uploads/2023/02/ABS-Cində-istehsal-edilən-SKoreya-ciplərinin-səviyyəsini-məhdudlasdira-bilər-scaled.jpg","title":"ABŞ Çində istehsal edilən S.Koreya çiplərinin səviyyəsini məhdudlaşdıra bilər – ABŞ rəsmisi","is_preview":true,"is_premium":false,"type":"__article_introduction__"}],"url":"https://www.az24saat.org/abs-cində-istehsal-edilən-s-koreya-ciplərinin-səviyyəsini-məhdudlasdira-bilər-abs-rəsmisi","is_premium":false,"is_preview":true,"total_count":1}