{"title":"Türkiyənin Malatya şəhərində 4,7 bal gücündə zəlzələ olub","content":[{"category":"cemiyyet","author":"azadsoz.com","published_at":"2023-02-25T11:00:00.000","image_url":"https://azadsoz.com/img/25795/thumbs/image_25795.jpeg","title":"Türkiyənin Malatya şəhərində 4,7 bal gücündə zəlzələ olub","is_preview":true,"is_premium":false,"type":"__article_introduction__"}],"url":"https://azadsoz.com/az/view/1/22766/turkiyenin_malatya_seherinde_47_bal_gucunde_zelzele_olub","is_premium":false,"is_preview":true,"total_count":1}