{"title":"Talıb Tale: “Bəxtiyar Hacıyev aclıq aksiyası keçirməklə nə edirsə, özünə, sağlamığına edir...”","content":[{"category":"soubiznes","author":"demokrat.az","published_at":"2023-02-25T14:31:00.000","image_url":"https://cdn.demokrat.az/uploadedfiles/custom/2023/2/25/1/8bb8e9b2-f2ff-4c8f-ab67-1bb93ebcd8ae/talib.jpg","title":"Talıb Tale: “Bəxtiyar Hacıyev aclıq aksiyası keçirməklə nə edirsə, özünə, sağlamığına edir...”","is_preview":true,"is_premium":false,"type":"__article_introduction__"}],"url":"https://demokrat.az/az/news/141186/talib-tale-bextiyar-haciyev-acliq-aksiyasi-kecirmekle-ne-edirse-ozune-saglamigina-edir","is_premium":false,"is_preview":true,"total_count":1}