{"title":"“Qarabağ”ın sabiq hücumçusu: “Çempionluğu çoxdan təmin ediblər”","content":[{"category":"idman","author":"report.az","published_at":"2023-02-25T14:52:00.000","image_url":"https://static.report.az/photo/64c27b2f-8e74-33ba-99b4-43b25401f08f_824.jpg","title":"“Qarabağ”ın sabiq hücumçusu: “Çempionluğu çoxdan təmin ediblər”","is_preview":true,"is_premium":false,"type":"__article_introduction__"}],"url":"https://report.az/futbol-xeberleri/qarabag-in-sabiq-hucumcusu-cempionlugu-coxdan-temin-edibler","is_premium":false,"is_preview":true,"total_count":1}