{"title":"Böyük ticarət mərkəzi açıldı: qazilərə və şahid ailələrinin işlə təminatına üstünlük veriləcək - VİDEO","content":[{"category":"diger","author":"olke.az","published_at":"2023-02-25T15:43:00.000","image_url":"https://olke.az/file/articles/2023/02/25/1677324390_qayali-qold-768x403.jpg","title":"Böyük ticarət mərkəzi açıldı: qazilərə və şahid ailələrinin işlə təminatına üstünlük veriləcək - VİDEO","is_preview":true,"is_premium":false,"type":"__article_introduction__"}],"url":"https://olke.az/cemiyyet/315768/byuk-ticaret-merkezi-acildi-qazilere-ve-sahid-ailelerinin-isle-teminatina-ustunluk-verilecek-video","is_premium":false,"is_preview":true,"total_count":1}