{"title":"\"Xocalıda azərbaycanlı qardaşlarımızın qətlini lənətləyirik\" - Çavuşoğlu","content":[{"category":"siyaset","author":"redaktor.az","published_at":"2023-02-26T09:20:00.000","image_url":"https://img.redaktor.az/news/2023/02/photo_195812.jpg","title":"\"Xocalıda azərbaycanlı qardaşlarımızın qətlini lənətləyirik\" - Çavuşoğlu","is_preview":true,"is_premium":false,"type":"__article_introduction__"}],"url":"https://redaktor.az/news/politics/195812-xocalida-azerbaycanli-qardaslarimizin-qetlini-lenetleyirik","is_premium":false,"is_preview":true,"total_count":1}