{"title":"İran yeni uzunmənzilli kruiz raketini təqdim etdi: “Təl-Əvivə asanlıqla çatır”","content":[{"category":"diger","author":"busaat.az","published_at":"2023-02-25T20:20:00.000","image_url":"https://static.busaat.az/core/storage/2023/02/kapak_135301.jpg","title":"İran yeni uzunmənzilli kruiz raketini təqdim etdi: “Təl-Əvivə asanlıqla çatır”","is_preview":true,"is_premium":false,"type":"__article_introduction__"}],"url":"https://busaat.az/iran-yeni-uzunmenzilli-kruiz-raketini-teqdim-etdi-tel-evive-asanliqla-catir","is_premium":false,"is_preview":true,"total_count":1}