{"title":"Səudiyyə Ərəbistanının Dəməşq qarşısında əsas şərti İranla bağlıdır","content":[{"category":"siyaset","author":"aqreqator.az","published_at":"2023-02-26T10:44:00.000","image_url":"https://aqreqator.az/img/pics/large/2023-02/1588850_fu4h0ucyev.jpg","title":"Səudiyyə Ərəbistanının Dəməşq qarşısında əsas şərti İranla bağlıdır","is_preview":true,"is_premium":false,"type":"__article_introduction__"}],"url":"https://aqreqator.az/az/siyaset/2415305","is_premium":false,"is_preview":true,"total_count":1}