{"title":"Baş Prokurorluğun həbs etdiyi məmurun istintaqı yekunlaşdı - 21 nəfər","content":[{"category":"olke","author":"qaynarinfo.az","published_at":"2023-02-27T17:55:00.000","image_url":"https://cdn.qaynarinfo.az/2023-02/1677506404_646e2033733e9f821c1e4e41d27002d6untitled-1-jpg.jpg","title":"Baş Prokurorluğun həbs etdiyi məmurun istintaqı yekunlaşdı - 21 nəfər","is_preview":true,"is_premium":false,"type":"__article_introduction__"}],"url":"https://qaynarinfo.az/az/bas-prokurorlugun-hebs-etdiyi-memurun-istintaqi-yekunlasdi-21-nefer","is_premium":false,"is_preview":true,"total_count":1}