{"title":"\"Tütün sənayesi ilə bağlı xüsusi proqram qəbul edilib\" - İQTİSADÇI-EKSPERT MÜNASİBƏT BİLDİRDİ","content":[{"category":"iqtisadiyyat","author":"sia.az","published_at":"2023-02-27T11:19:00.000","image_url":"https://sia.az/storage/2021/02/12/tutun-operasyonu.jpg","title":"\"Tütün sənayesi ilə bağlı xüsusi proqram qəbul edilib\" - İQTİSADÇI-EKSPERT MÜNASİBƏT BİLDİRDİ","is_preview":true,"is_premium":false,"type":"__article_introduction__"}],"url":"https://sia.az/az/news/economy/1037971.html","is_premium":false,"is_preview":true,"total_count":1}