{"title":"RUSİYA RƏHBƏRLİYİ TƏHDİDİN DOZASINI ARTIRIR... – “Keçmiş həyat əsrlər boyu unudulmalı olacaq\"","content":[{"category":"gundem","author":"azpolitika.info","published_at":"2023-02-27T12:20:00.000","image_url":"https://static.azpolitika.info/storage/news/460d8165f381c676ca6cc89c40df5451/7eb201c3-236c-4574-af6e-4e3fea744d1d.jpg","title":"RUSİYA RƏHBƏRLİYİ TƏHDİDİN DOZASINI ARTIRIR... – “Keçmiş həyat əsrlər boyu unudulmalı olacaq\"","is_preview":true,"is_premium":false,"type":"__article_introduction__"}],"url":"https://azpolitika.info/?p=706855","is_premium":false,"is_preview":true,"total_count":1}