{"title":"Azərbaycanda ticarət dövriyyəsinin yarısı Bakının payına düşür","content":[{"category":"idman","author":"yenicag.az","published_at":"2023-02-27T21:38:26.000","image_url":"https://cdn.yenicag.az/files/uploads/2022/11/ticaret_liman.jpg","title":"Azərbaycanda ticarət dövriyyəsinin yarısı Bakının payına düşür","is_preview":true,"is_premium":false,"type":"__article_introduction__"}],"url":"https://yenicag.az/azerbaycanda-ticaret-dovriyyesinin-yarisi-bakinin-payina-dusur","is_premium":false,"is_preview":true,"total_count":1}