{"title":"Şeyxülislam Allahşükür Paşazadə ABŞ-yə səfərə gedib","content":[{"category":"siyaset","author":"azerbaijan-news.az","published_at":"2023-02-27T11:59:00.000","image_url":"https://www.azerbaijan-news.az/uploads/img/posts/2023/02/27/16774834714609937934_1200x630jpg-1677484764.jpg","title":"Şeyxülislam Allahşükür Paşazadə ABŞ-yə səfərə gedib","is_preview":true,"is_premium":false,"type":"__article_introduction__"}],"url":"https://www.azerbaijan-news.az/az/posts/detail/olkemizdeki-dini-konfessiya-rehberleri-xocali-soyqirimi-qurbanlarini-aniblar-1677427065","is_premium":false,"is_preview":true,"total_count":1}