{"title":"\"Öz xahişi ilə çıxmışdı\" - DİN-dən \"Aşıq Muşqulat\"la bağlı açıqlama","content":[{"category":"diger","author":"azvision.az","published_at":"2023-02-27T12:46:00.000","image_url":"https://azvision.az/photos/2023/02/Screenshot_5-1677487482.jpg","title":"\"Öz xahişi ilə çıxmışdı\" - DİN-dən \"Aşıq Muşqulat\"la bağlı açıqlama","is_preview":true,"is_premium":false,"type":"__article_introduction__"}],"url":"https://www.azvision.az/news/320696/---oz-xahisi-ile-cixmisdi---din-den--asiq-musqulat-la-bagli-aciqlama---.html","is_premium":false,"is_preview":true,"total_count":1}