{"title":"Qarabağ zonasında daha 384 hektar ərazi minalardan təmizlənib","content":[{"category":"diger","author":"mia.az","published_at":"2023-02-27T10:56:00.000","image_url":"https://mia.az/uploads/img/posts/2021/04/24/mina-azerbjpg-1619248459.jpg","title":"Qarabağ zonasında daha 384 hektar ərazi minalardan təmizlənib","is_preview":true,"is_premium":false,"type":"__article_introduction__"}],"url":"https://mia.az/w1045125/qarabag-zonasinda-daha-384-hektar-erazi-minalardannbsptemizlenib-2023-02-27-110008","is_premium":false,"is_preview":true,"total_count":1}