{"title":"SABİQ ŞAHZADƏ MÖVCUD REJİMƏ QARŞI – İran müxalifəti “keçid hökuməti” formalaşdıra bilərmi?","content":[{"category":"siyaset","author":"azpolitika.info","published_at":"2023-02-27T08:40:00.000","image_url":"https://static.azpolitika.info/storage/news/de4b5ae597d04d1ae2c1b209d9c2bfca/3f1f23d6-ef1c-4cb4-a531-e73fc35b7aad.jpg","title":"SABİQ ŞAHZADƏ MÖVCUD REJİMƏ QARŞI – İran müxalifəti “keçid hökuməti” formalaşdıra bilərmi?","is_preview":true,"is_premium":false,"type":"__article_introduction__"}],"url":"https://azpolitika.info/?p=706822","is_premium":false,"is_preview":true,"total_count":1}