{"title":"\"Əsrin fəlakəti\"ni yaşayan Türkiyənin infrastruktura dəyən ziyan neçə milyard dollardır? - ARAŞDIRMA","content":[{"category":"diger","author":"big.az","published_at":"2023-02-26T22:18:02.000","image_url":"https://upload.az/foto/arxiv/CwqNciWz90spaT0brloSaP7pQiTFuuooej8XEs4g.jpg","title":"\"Əsrin fəlakəti\"ni yaşayan Türkiyənin infrastruktura dəyən ziyan neçə milyard dollardır? - ARAŞDIRMA","is_preview":true,"is_premium":false,"type":"__article_introduction__"}],"url":"https://big.az/496000-esrin-felaketini-yasayan-turkiyenin-infrastruktura-deyen-ziyan-nece-milyard-dollardir-arasdirma.html","is_premium":false,"is_preview":true,"total_count":1}