{"title":"Bakıda dövlət qurumu dənizkənarı ərazidə qanunsuz tikilini sökdü - FOTO","content":[{"category":"hadise","author":"moderator.az","published_at":"2023-02-27T14:49:00.000","image_url":"https://moderator.az/file/articles/2023/02/27/1677495311_40.jpg","title":"Bakıda dövlət qurumu dənizkənarı ərazidə qanunsuz tikilini sökdü - FOTO","is_preview":true,"is_premium":false,"type":"__article_introduction__"}],"url":"https://moderator.az/az/hadise/604516/bakida-dvlet-qurumu-denizkenari-erazide-qanunsuz-tikilini-skdu-foto","is_premium":false,"is_preview":true,"total_count":1}