{"title":"Azərbaycan və Ermənistan onlayn danışıqlara keçib - “Nezavisimaya qazeta”","content":[{"category":"siyaset","author":"dia.az","published_at":"2023-02-27T12:04:00.000","image_url":"https://dia.az/uploads/posts/2023-02/thumbs/1677485043_0001.jpg","title":"Azərbaycan və Ermənistan onlayn danışıqlara keçib - “Nezavisimaya qazeta”","is_preview":true,"is_premium":false,"type":"__article_introduction__"}],"url":"https://www.dia.az/8/368373-azerbaycan-ve-ermenistan-onlayn-danishiqlara-kechib.html","is_premium":false,"is_preview":true,"total_count":1}