{"title":"Zelenski və nazirlər niyə hərbi forma geyinirlər? - Baş nazir səbəbi açıqlayıb","content":[{"category":"siyaset","author":"ayna.az","published_at":"2023-02-26T17:47:00.000","image_url":"https://ayna.az/uploads/images/2023/02/image_750x500_63fb59364498e.jpg","title":"Zelenski və nazirlər niyə hərbi forma geyinirlər? - Baş nazir səbəbi açıqlayıb","is_preview":true,"is_premium":false,"type":"__article_introduction__"}],"url":"https://ayna.az/zelenski-ve-nazirler-niye-herbi-forma-geyinirler-bas-nazir-sebebi-aciqlayib","is_premium":false,"is_preview":true,"total_count":1}