{"title":"Dünya Bankı zəlzələnin vurduğu ziyanı hesabladı","content":[{"category":"diger","author":"yenigundem.az","published_at":"2023-02-27T17:27:00.000","image_url":"https://yenigundem.az/wp-content/uploads/2023/02/yenigundem_bc2919c1f1acc09a3a3eaf4abae00c6e_cfjwi957rshg1m0tv2u6.jpg","title":"Dünya Bankı zəlzələnin vurduğu ziyanı hesabladı","is_preview":true,"is_premium":false,"type":"__article_introduction__"}],"url":"https://yenigundem.az/dunya-banki-zelzelenin-vurdugu-ziyani-hesabladi","is_premium":false,"is_preview":true,"total_count":1}