{"title":"Nazirliyin tabeliyində agentliklərin yaradılması may ayı üçün nəzərdə tutulub","content":[{"category":"cemiyyet","author":"teleqraf.com","published_at":"2023-02-27T15:54:34.000","image_url":"https://teleqraf.com/storage/2023/02/27/emrullayev_emin.jpg","title":"Nazirliyin tabeliyində agentliklərin yaradılması may ayı üçün nəzərdə tutulub","is_preview":true,"is_premium":false,"type":"__article_introduction__"}],"url":"https://teleqraf.com/news/toplum/368862.html","is_premium":false,"is_preview":true,"total_count":1}