{"title":"Son nəfəsini avtobusda verən Xalq artisti: “Həmişə qorxurdu ki…” – FOTOLAR","content":[{"category":"idman","author":"yenicag.az","published_at":"2023-02-28T14:46:10.000","image_url":"https://cdn.yenicag.az/files/uploads/2023/02/agaxan-salmanli.jpg","title":"Son nəfəsini avtobusda verən Xalq artisti: “Həmişə qorxurdu ki…” – FOTOLAR","is_preview":true,"is_premium":false,"type":"__article_introduction__"}],"url":"https://yenicag.az/son-nefesini-avtobusda-veren-xalq-artisti-hemise-qorxurdu-ki-fotolar","is_premium":false,"is_preview":true,"total_count":1}