{"title":"\"Mədəniyyət sahəsində fəaliyyət tədbirçilik üzərində qurulub\" - Adil Kərimli","content":[{"category":"diger","author":"azvision.az","published_at":"2023-02-28T12:11:00.000","image_url":"https://azvision.az/photos/2023/02/1677569860_22-1677571960.jpg","title":"\"Mədəniyyət sahəsində fəaliyyət tədbirçilik üzərində qurulub\" - Adil Kərimli","is_preview":true,"is_premium":false,"type":"__article_introduction__"}],"url":"https://www.azvision.az/news/320791/--medeniyyet-sahesinde-fealiyyet-tedbircilik-uzerinde-qurulub--adil-kerimli--  .html","is_premium":false,"is_preview":true,"total_count":1}