{"title":"Ukraynada rusiyalı iş adamlarının müəssisələrinə həbs qoyulub","content":[{"category":"siyaset","author":"moderator.az","published_at":"2023-02-28T20:13:00.000","image_url":"https://moderator.az/file/articles/2023/02/28/1677600911_25636200-aaa4-3610-ae06-3511debb31b8_850.jpg","title":"Ukraynada rusiyalı iş adamlarının müəssisələrinə həbs qoyulub","is_preview":true,"is_premium":false,"type":"__article_introduction__"}],"url":"https://moderator.az/az/dunya/605093/ukraynada-rusiyali-is-adamlarinin-muessiselerine-hebs-qoyulub","is_premium":false,"is_preview":true,"total_count":1}