{"title":"Ağ şəhər sakinləri: “Evlərimiz razılığımız olmadan sökülüb”","content":[{"category":"diger","author":"toplum.tv","published_at":"2023-03-01T12:30:48.000","image_url":"https://toplum.tv/images/2023-03/1677657079513.jpg","title":"Ağ şəhər sakinləri: “Evlərimiz razılığımız olmadan sökülüb”","is_preview":true,"is_premium":false,"type":"__article_introduction__"}],"url":"https://toplum.tv/qaynar-xett/pag-seher-sakinleri-ldquoevlerimiz-raziligimiz-olmadan-soumlkuumlluumlbrdquonbspp","is_premium":false,"is_preview":true,"total_count":1}