{"title":"Madonna qardaşının ölümü haqqında görün nələr dedi - FOTO","content":[{"category":"soubiznes","author":"sfera.az","published_at":"2023-03-01T00:38:00.000","image_url":"https://sfera.az/file/articles/2023/03/01/1677617445_mad.jpg","title":"Madonna qardaşının ölümü haqqında görün nələr dedi - FOTO","is_preview":true,"is_premium":false,"type":"__article_introduction__"}],"url":"https://sfera.az/maqazin/211487/madonna-qardasinin-lumu-haqqinda-grun-neler-dedi-foto","is_premium":false,"is_preview":true,"total_count":1}