{"title":"Azərbaycanda ayrı-seçkiliyə daha çox kimlər məruz qalır?","content":[{"category":"diger","author":"toplum.tv","published_at":"2023-03-01T01:13:02.000","image_url":"https://toplum.tv/images/2023-03/1677669899795.jpg","title":"Azərbaycanda ayrı-seçkiliyə daha çox kimlər məruz qalır?","is_preview":true,"is_premium":false,"type":"__article_introduction__"}],"url":"https://toplum.tv/toplumsal/pazerbaycanda-ayri-seccedilkiliye-daha-ccedilox-kimler-meruz-qalirp","is_premium":false,"is_preview":true,"total_count":1}