{"title":"Ulu Öndər Heydər Əliyev və milli dövlətçilik təfəkkürü","content":[{"category":"gundem","author":"xalqxeber.az","published_at":"2023-02-28T16:01:56.000","image_url":"https://xalqxeber.az/uploads/posts/2023-02/1677585743_whatsapp-mage-2023-02-28-at-15_43_55.jpeg","title":"Ulu Öndər Heydər Əliyev və milli dövlətçilik təfəkkürü","is_preview":true,"is_premium":false,"type":"__article_introduction__"}],"url":"https://xalqxeber.az/agenda/89655-ulu-onder-heyder-eliyev-ve-milli-dovletchilik-tefekkuru.html","is_premium":false,"is_preview":true,"total_count":1}