{"title":"Adıyamanda baş verən zəlzələ zamanı göldən alovlar yüksəlib","content":[{"category":"diger","author":"7news.az","published_at":"2023-03-01T11:44:00.000","image_url":"https://www.7news.az/photo/520x400/2023-03/1677655808_iu90.jpg","title":"Adıyamanda baş verən zəlzələ zamanı göldən alovlar yüksəlib","is_preview":true,"is_premium":false,"type":"__article_introduction__"}],"url":"https://www.7news.az/az/adiyamanda-bas-veren-zelzele-zamani-glden-alovlar-yukselib","is_premium":false,"is_preview":true,"total_count":1}