{"title":"Skandinaviya ölkəsindən əlamətdar qərar: Rusiya ilə sərhədlərini hasarlamağa başladılar!","content":[{"category":"diger","author":"az24saat.org","published_at":"2023-02-28T19:19:13.000","image_url":"https://www.az24saat.org/wp-content/uploads/2023/02/Skandinaviya-olkəsindən-əlamətdar-qərar-Rusiya-ilə-sərhədlərini-hasarlamaga-basladilar.jpg","title":"Skandinaviya ölkəsindən əlamətdar qərar: Rusiya ilə sərhədlərini hasarlamağa başladılar!","is_preview":true,"is_premium":false,"type":"__article_introduction__"}],"url":"https://www.az24saat.org/skandinaviya-olkəsindən-əlamətdar-qərar-rusiya-ilə-sərhədlərini-hasarlamaga-basladilar","is_premium":false,"is_preview":true,"total_count":1}