{"title":"Din və məhəbbət - faciələrə aparan ziddiyyət - Telman Orucov yazır","content":[{"category":"diger","author":"525.az","published_at":"2023-03-01T21:00:00.000","image_url":"https://525.az/img/pics/large/2022-06/229548_4az6e84pj9.jpg","title":"Din və məhəbbət - faciələrə aparan ziddiyyət - Telman Orucov yazır","is_preview":true,"is_premium":false,"type":"__article_introduction__"}],"url":"https://525.az/news/215432-din-ve-mehebbet-facielere-aparan-ziddiyyet--telman-orucov-yazir","is_premium":false,"is_preview":true,"total_count":1}