{"title":"“Müharibə daha üç il davam edə bilər”","content":[{"category":"herbi","author":"7times.az","published_at":"2023-03-01T07:54:00.000","image_url":"https://7times.az/public/cloud/2023/03/seventimes_9f66f325a0a47ec8f923fdd69edfeb35_cpu4kng3iy15eowl089v.jpg","title":"“Müharibə daha üç il davam edə bilər”","is_preview":true,"is_premium":false,"type":"__article_introduction__"}],"url":"https://7times.az/muharibe-daha-uc-il-davam-ede-biler","is_premium":false,"is_preview":true,"total_count":1}