{"title":"Osmaniyedə 4,1 bal gücündə zəlzələ!","content":[{"category":"diger","author":"nocomment.az","published_at":"2023-02-28T15:04:00.000","image_url":"https://nocomment.az/public/cloud/2020/03/nocomment_0be011a7a2758922a87a0e23583bf1b6_q2mbr60wla31sgvzucfn-e1584814822449.jpg","title":"Osmaniyedə 4,1 bal gücündə zəlzələ!","is_preview":true,"is_premium":false,"type":"__article_introduction__"}],"url":"https://nocomment.az/osmaniyede-4-1-bal-gucunde-zelzele","is_premium":false,"is_preview":true,"total_count":1}