{"title":"Mayakovski sakinləri NƏDƏN VƏ NİYƏ NARAHATDIR? - MÜRACİƏT","content":[{"category":"siyaset","author":"dia.az","published_at":"2023-02-28T09:22:00.000","image_url":"https://dia.az/uploads/posts/2023-02/thumbs/1677561644_0001.jpg","title":"Mayakovski sakinləri NƏDƏN VƏ NİYƏ NARAHATDIR? - MÜRACİƏT","is_preview":true,"is_premium":false,"type":"__article_introduction__"}],"url":"https://www.dia.az/1/368461-mayakovski-sakinleri-neden-ve-nye-narahatdr.html","is_premium":false,"is_preview":true,"total_count":1}