{"title":"AK rəhbəri: “Ticarət sazişi Aİ-Böyük Britaniya əməkdaşlığında yeni səhifə açır”","content":[{"category":"diger","author":"interpress.az","published_at":"2023-02-28T11:00:25.000","image_url":"https://interpress.az/public/cloud/2023/02/interpress_352a5fbbc2114ccde9b0c3966a6173c5_4pekqabmu7295olsc0vx.jpg","title":"AK rəhbəri: “Ticarət sazişi Aİ-Böyük Britaniya əməkdaşlığında yeni səhifə açır”","is_preview":true,"is_premium":false,"type":"__article_introduction__"}],"url":"https://interpress.az/ak-rehberi-ticaret-sazisi-ai-boyuk-britaniya-emekdasliginda-yeni-sehife-acir.html","is_premium":false,"is_preview":true,"total_count":1}