{"title":"Çavuşoğlu Lavrovla Hindistanda görüşdü","content":[{"category":"siyaset","author":"modern.az","published_at":"2023-03-01T13:13:31.000","image_url":"https://files.modern.az/articles/2023/03/01/1677662638_1677662541_1677662064_6c89c1d9-c829-491c-ad96-4f0f2b35c58f.jpg","title":"Çavuşoğlu Lavrovla Hindistanda görüşdü","is_preview":true,"is_premium":false,"type":"__article_introduction__"}],"url":"https://modern.az/dunya/398445/avusolu-lavrovla-hindistanda-grusdu","is_premium":false,"is_preview":true,"total_count":1}