{"title":"Bu ev heyvanlarının satışında rekord göstərici: “Zəlzələni 3 dəqiqə qabaq xəbər verirlər”","content":[{"category":"maraqli","author":"savash.org","published_at":"2023-03-01T19:09:32.000","image_url":"https://www.savash.org/wp-content/uploads/2023/02/zelzele1.jpg","title":"Bu ev heyvanlarının satışında rekord göstərici: “Zəlzələni 3 dəqiqə qabaq xəbər verirlər”","is_preview":true,"is_premium":false,"type":"__article_introduction__"}],"url":"https://savash.org/maraql/59468-bu-ev-heyvanlarinin-satisinda-rekord-gostərici-zəlzələni-3-dəqiqə-qabaq-xəbər-verirlər.html","is_premium":false,"is_preview":true,"total_count":1}