{"title":"Dava saldı, 12 min dollar zərər verdi","content":[{"category":"medeniyyet","author":"olay.az","published_at":"2023-03-02T11:10:00.000","image_url":"https://olay.az/uploads/posts/2023-03/1677740870_ae3e19eaa2207fc5c44cb44bd4204ed2.jpg","title":"Dava saldı, 12 min dollar zərər verdi","is_preview":true,"is_premium":false,"type":"__article_introduction__"}],"url":"https://olay.az/media/musiqi/13557-dava-saldi-12-min-dollar-zerer-verdi.html","is_premium":false,"is_preview":true,"total_count":1}