{"title":"İran prezidenti məktəbli qızların xəstələnməsi ilə bağlı araşdırmaya göstəriş verib","content":[{"category":"diger","author":"amerikaninsesi.org","published_at":"2023-03-01T18:03:40.000","image_url":"https://gdb.voanews.com/562ade44-bb79-473f-831f-34dea2386df7_w1200_r1.jpg","title":"İran prezidenti məktəbli qızların xəstələnməsi ilə bağlı araşdırmaya göstəriş verib","is_preview":true,"is_premium":false,"type":"__article_introduction__"}],"url":"https://www.amerikaninsesi.org/a/iran-president-ebrahim-raisi-investigation-/6985364.html","is_premium":false,"is_preview":true,"total_count":1}