{"title":"“Ötən il Azərbaycan-Özbəkistan münasibətlərinin inkişafında rekord il olub” - İlham Əliyev","content":[{"category":"siyaset","author":"manset.az","published_at":"2023-03-01T22:10:00.000","image_url":"https://manset.az//storage/2023/march/01/40jpg_16776939231677694259.jpg","title":"“Ötən il Azərbaycan-Özbəkistan münasibətlərinin inkişafında rekord il olub” - İlham Əliyev","is_preview":true,"is_premium":false,"type":"__article_introduction__"}],"url":"https://manset.az/news/62729/oten-il-azerbaycan-ozbekistan-munasibetlerinin-inkisafinda-rekord-il-olub-ilham-eliyev","is_premium":false,"is_preview":true,"total_count":1}