{"title":"Prezident: \"Azərbaycanın azad olunmuş əraziləri klassik urbisid, kultursid və ekosid nümunələridir\"","content":[{"category":"siyaset","author":"525.az","published_at":"2023-03-02T11:12:00.000","image_url":"https://525.az/img/pics/large/2023-01/253234_5k7sudtd1r.jpg","title":"Prezident: \"Azərbaycanın azad olunmuş əraziləri klassik urbisid, kultursid və ekosid nümunələridir\"","is_preview":true,"is_premium":false,"type":"__article_introduction__"}],"url":"https://525.az/news/215554-prezident-azerbaycanin-azad-olunmus-erazileri-klassik-urbisid-kultursid-ve-ekosid-numuneleridir","is_premium":false,"is_preview":true,"total_count":1}