{"title":"Ermənistanın keçmiş ordu rəhbərləri yenidən sorğu-sual ediləcəklər","content":[{"category":"siyaset","author":"azvision.az","published_at":"2023-03-02T11:11:00.000","image_url":"https://azvision.az/photos/2023/03/khjkhjkh-1677741117.jpg","title":"Ermənistanın keçmiş ordu rəhbərləri yenidən sorğu-sual ediləcəklər","is_preview":true,"is_premium":false,"type":"__article_introduction__"}],"url":"https://www.azvision.az/news/321032/-ermenistanin-kecmis-ordu-rehberleri-yeniden-sorgu-sual-edilecekler-.html","is_premium":false,"is_preview":true,"total_count":1}