{"title":"\"Tottenhem\"in baş məşqçisi azarkeşlərdən üzr istədi","content":[{"category":"idman","author":"qol.az","published_at":"2023-03-02T12:30:47.000","image_url":"https://qol.az/img/pics/large/2023-03/178529_kxw561g2ew.jpg","title":"\"Tottenhem\"in baş məşqçisi azarkeşlərdən üzr istədi","is_preview":true,"is_premium":false,"type":"__article_introduction__"}],"url":"https://qol.az/news/184592-tottenhemin-bas-mesqcisi-azarkeslerden-uzr-istedi","is_premium":false,"is_preview":true,"total_count":1}